generator/__init__.py
generator/generator.py
generator_dates-0.2.5.dist-info/LICENSE
generator_dates-0.2.5.dist-info/METADATA
generator_dates-0.2.5.dist-info/WHEEL
generator_dates-0.2.5.dist-info/top_level.txt
generator_dates-0.2.5.dist-info/RECORD
