Metadata-Version: 2.2
Name: generator_dates
Version: 0.2.5
Summary: A Python package to generate random dates in different formats and languages.
Home-page: https://github.com/Triram-2/generator_dates
Author: Misha
Author-email: bobyyy239@gmail.com
Classifier: Programming Language :: Python :: 3
Classifier: License :: OSI Approved :: MIT License
Classifier: Operating System :: OS Independent
Requires-Python: >=3.6
License-File: LICENSE
Dynamic: author
Dynamic: author-email
Dynamic: classifier
Dynamic: description
Dynamic: description-content-type
Dynamic: home-page
Dynamic: requires-python
Dynamic: summary
